larakit/__init__.py
larakit/_core.py
larakit/_lang.py
larakit/math.py
larakit/pipeline.py
larakit/progressbar.py
larakit/shell.py
larakit/corpus/__init__.py
larakit/corpus/_base.py
larakit/corpus/_jtm.py
larakit/corpus/_parallel.py
larakit/corpus/_tmx.py
larakit-1.6.3.dist-info/licenses/LICENSE
larakit-1.6.3.dist-info/METADATA
larakit-1.6.3.dist-info/WHEEL
larakit-1.6.3.dist-info/top_level.txt
larakit-1.6.3.dist-info/RECORD
