Metadata-Version: 2.4
Name: larakit
Version: 1.6.3
Summary: Python common components for Lara
Author-email: Translated <support@laratranslate.com>
Maintainer-email: Translated <support@laratranslate.com>
License: Copyright (c) 2025 Translated
Project-URL: Homepage, https://github.com/translated/larakit
Project-URL: Source, https://github.com/translated/larakit
Classifier: Programming Language :: Python :: 3
Classifier: License :: OSI Approved :: MIT License
Classifier: Operating System :: OS Independent
Requires-Python: >=3.9
License-File: LICENSE
Dynamic: license-file
